json_loader_with_include/__init__.py
json_loader_with_include/json_loader.py
json_loader_with_include-0.3.3.dist-info/licenses/LICENSE
tests/__init__.py
tests/test_json_loader.py
json_loader_with_include-0.3.3.dist-info/METADATA
json_loader_with_include-0.3.3.dist-info/WHEEL
json_loader_with_include-0.3.3.dist-info/top_level.txt
json_loader_with_include-0.3.3.dist-info/RECORD
